{
  "openapi": "3.0.1",
  "info": {
    "version": "1.0.0",
    "title": "YourPet API docs",
    "description": "*Backend documentation for YourPet-project*"
  },
  "consumes": ["application/json", "multipart/form-data"],
  "produces": ["application/json"],
  "servers": [
    { "url": "http://localhost:5000" },
    { "url": "https://your-pet-backend-nci6.onrender.com" }
  ],
  "tags": [
    {
      "name": "Users",
      "description": "Authorization/User endpoints"
    },
    {
      "name": "Notices",
      "description": "Notices endpoints"
    },
    {
      "name": "Pets",
      "description": "Pets endpoints"
    },
    {
      "name": "News",
      "description": "News endpoint"
    },
    {
      "name": "Friends",
      "description": "Friends endpoint"
    }
  ],
  "paths": {
    "/api/users/register": {
      "post": {
        "tags": ["Users"],
        "summary": "User registration",
        "requestBody": {
          "description": "Registration's object",
          "required": true,
          "content": {
            "application/json": {
              "schema": {
                "$ref": "#/components/schemas/RegistrationRequest"
              }
            }
          }
        },
        "responses": {
          "201": {
            "description": "Successful operation",
            "content": {
              "application/json": {
                "schema": {
                  "$ref": "#/components/schemas/RegistrationResponse"
                }
              }
            }
          },
          "400": {
            "description": "Bad request (invalid request body)",
            "content": {
              "application/json": {
                "schema": {
                  "$ref": "#/components/schemas/RegistrationResponse400"
                }
              }
            }
          },
          "409": {
            "description": "Conflict (Provided email already exists)",
            "content": {
              "application/json": {
                "schema": {
                  "$ref": "#/components/schemas/RegistrationResponse409"
                }
              }
            }
          }
        }
      }
    },
    "/api/users/login": {
      "post": {
        "tags": ["Users"],
        "summary": "User login",
        "requestBody": {
          "description": "Login object",
          "required": true,
          "content": {
            "application/json": {
              "schema": {
                "$ref": "#/components/schemas/LoginRequest"
              }
            }
          }
        },
        "responses": {
          "201": {
            "description": "Successful operation",
            "content": {
              "application/json": {
                "schema": {
                  "$ref": "#/components/schemas/LoginResponse"
                }
              }
            }
          },
          "400": {
            "description": "Bad request (invalid request body)",
            "content": {
              "application/json": {
                "schema": {
                  "$ref": "#/components/schemas/LoginResponse400"
                }
              }
            }
          },
          "401": {
            "description": "Unauthorized (wrong login information)",
            "content": {
              "application/json": {
                "schema": {
                  "$ref": "#/components/schemas/LoginResponse401"
                }
              }
            }
          },
          "404": {
            "description": "Not Found",
            "content": {
              "application/json": {
                "schema": {
                  "$ref": "#/components/schemas/Response404"
                }
              }
            }
          }
        }
      }
    },
    "/api/users/logout": {
      "post": {
        "tags": ["Users"],
        "summary": "User logout",
        "security": [{ "Bearer": [] }],
        "responses": {
          "204": {
            "description": "Successful operation",
            "content": {}
          },
          "401": {
            "description": "Unauthorized (wrong login information)",
            "content": {
              "application/json": {
                "schema": {
                  "$ref": "#/components/schemas/Response401"
                }
              }
            }
          },
          "404": {
            "description": "Not Found",
            "content": {
              "application/json": {
                "schema": {
                  "$ref": "#/components/schemas/Response404"
                }
              }
            }
          }
        }
      }
    },
    "/api/users/edit-profile": {
      "patch": {
        "tags": ["Users"],
        "summary": "Edit user's information",
        "security": [{ "Bearer": [] }],
        "requestBody": {
          "description": "Edit-user object",
          "required": true,
          "content": {
            "multipart/form-data": {
              "schema": {
                "$ref": "#/components/schemas/EditUserRequest"
              }
            }
          }
        },
        "responses": {
          "200": {
            "description": "Successful operation",
            "content": {
              "application/json": {
                "schema": {
                  "$ref": "#/components/schemas/EditUserResponse"
                }
              }
            }
          },
          "400": {
            "description": "Bad request (invalid request body)",
            "content": {
              "application/json": {
                "schema": {
                  "$ref": "#/components/schemas/RegistrationResponse400"
                }
              }
            }
          },
          "401": {
            "description": "Unauthorized (wrong login information)",
            "content": {
              "application/json": {
                "schema": {
                  "$ref": "#/components/schemas/Response401"
                }
              }
            }
          },
          "404": {
            "description": "Not Found",
            "content": {
              "application/json": {
                "schema": {
                  "$ref": "#/components/schemas/Response404"
                }
              }
            }
          },
          "409": {
            "description": "Conflict (user with stated email is already exist)",
            "content": {
              "application/json": {
                "schema": {
                  "$ref": "#/components/schemas/RegistrationResponse409"
                }
              }
            }
          }
        }
      }
    },
    "/api/users/current": {
      "post": {
        "tags": ["Users"],
        "summary": "User login",
        "requestBody": {
          "description": "Login object",
          "required": true,
          "content": {
            "application/json": {
              "schema": {
                "$ref": "#/components/schemas/LoginRequest"
              }
            }
          }
        },
        "responses": {
          "201": {
            "description": "Successful operation",
            "content": {
              "application/json": {
                "schema": {
                  "$ref": "#/components/schemas/LoginResponse"
                }
              }
            }
          },
          "400": {
            "description": "Bad request (invalid request body)",
            "content": {
              "application/json": {
                "schema": {
                  "$ref": "#/components/schemas/LoginResponse400"
                }
              }
            }
          },
          "401": {
            "description": "Unauthorized (wrong login information)",
            "content": {
              "application/json": {
                "schema": {
                  "$ref": "#/components/schemas/LoginResponse401"
                }
              }
            }
          },
          "404": {
            "description": "Not Found",
            "content": {
              "application/json": {
                "schema": {
                  "$ref": "#/components/schemas/Response404"
                }
              }
            }
          }
        }
      }
    }
  },
  "components": {
    "schemas": {
      "RegistrationRequest": {
        "type": "object",
        "required": ["email", "password"],
        "properties": {
          "email": {
            "type": "string",
            "description": "User's email",
            "format": "email"
          },
          "password": {
            "type": "string",
            "description": "User's password",
            "example": "qwerty123"
          }
        }
      },
      "RegistrationResponse": {
        "type": "array",
        "items": {
          "type": "object",
          "properties": {
            "email": {
              "type": "string",
              "description": "User's email",
              "format": "email"
            },
            "userId": {
              "type": "number",
              "description": "User's id",
              "example": "32143232436545474"
            }
          }
        },
        "example": [
          { "email": "1@gmail.com", "userId": "1" },
          { "email": "2@gmail.com", "userId": "2" }
        ]
      }
    },
    "securitySchemes": {
      "Bearer": {
        "type": "http",
        "scheme": "bearer",
        "bearerFormat": "JWT"
      }
    }
  }
}
